sat/__init__.py
sat/arguments.py
sat/helpers.py
sat/transformer_defaults.py
sat/data_utils/__init__.py
sat/data_utils/configure_data.py
sat/data_utils/datasets.py
sat/data_utils/hf_dataset.py
sat/data_utils/jsonlds.py
sat/data_utils/samplers.py
sat/data_utils/webds.py
sat/generation/__init__.py
sat/generation/autoregressive_sampling.py
sat/generation/cuda2d_sampling.py
sat/generation/magnify.py
sat/generation/utils.py
sat/generation/sampling_strategies/__init__.py
sat/generation/sampling_strategies/base_strategy.py
sat/generation/sampling_strategies/beam_search_strategy.py
sat/generation/sampling_strategies/iterative_entfilter_strategy.py
sat/model/__init__.py
sat/model/base_model.py
sat/model/cached_autoregressive_model.py
sat/model/encoder_decoder_model.py
sat/model/mixins.py
sat/model/registry.py
sat/model/transformer.py
sat/model/attention/__init__.py
sat/model/attention/memory_efficient_attention.py
sat/model/finetune/__init__.py
sat/model/finetune/adapter.py
sat/model/finetune/ffadd.py
sat/model/finetune/lora.py
sat/model/finetune/lora2.py
sat/model/finetune/mlp_head.py
sat/model/finetune/prompt_tuning.py
sat/model/official/__init__.py
sat/model/official/bert_model.py
sat/model/official/cait_model.py
sat/model/official/chatglm2_model.py
sat/model/official/chatglm3_model.py
sat/model/official/chatglm4_model.py
sat/model/official/chatglm_model.py
sat/model/official/clip_model.py
sat/model/official/cuda2d_model.py
sat/model/official/distill_model.py
sat/model/official/dpr_model.py
sat/model/official/eva2_model.py
sat/model/official/eva_clip_model.py
sat/model/official/glm130B_model.py
sat/model/official/glm4v_model.py
sat/model/official/glm_model.py
sat/model/official/gpt2_model.py
sat/model/official/gptneo_model.py
sat/model/official/llama_model.py
sat/model/official/mae_model.py
sat/model/official/mixtral_model.py
sat/model/official/roberta_model.py
sat/model/official/t5_model.py
sat/model/official/vit_model.py
sat/model/official/yolos_model.py
SwissArmyTransformer-0.4.12.dist-info/LICENSE
SwissArmyTransformer-0.4.12.dist-info/METADATA
SwissArmyTransformer-0.4.12.dist-info/WHEEL
SwissArmyTransformer-0.4.12.dist-info/top_level.txt
SwissArmyTransformer-0.4.12.dist-info/RECORD
