Metadata-Version: 2.1
Name: SwissArmyTransformer
Version: 0.4.12
Summary: A transformer-based framework with finetuning as the first class citizen.
Home-page: https://github.com/THUDM/SwissArmyTransformer
Author: Ming Ding, et al.
Author-email: dm_thu@qq.com
License: Apache 2.0 license
Requires-Python: >=3.5
License-File: LICENSE
Requires-Dist: torch
Requires-Dist: deepspeed
Requires-Dist: sentencepiece
Requires-Dist: tensorboardX
Requires-Dist: datasets
Requires-Dist: transformers
Requires-Dist: cpm-kernels
Requires-Dist: einops
Requires-Dist: boto3
Requires-Dist: webdataset
